{
    "NODE": [
        {
            "ID": 1,
            "LOCALTION": "local",
            "MACHINE": "physical",
            "IPV6": "fec0::3dc9:cc33:37de:42bd",
            "FRAME": "riscv64",
            "NIC": "",
            "MAC": "cat: /sys/class/net//address: No such file or directory",
            "IPV4": "127.0.0.1",
            "USER": "root",
            "PASSWORD": "openEuler12#$",
            "SSH_PORT": 22,
            "BMC_IP": "",
            "BMC_USER": "",
            "BMC_PASSWORD": ""
        },
        {
            "ID": 2,
            "LOCALTION": "local",
            "MACHINE": "physical",
            "IPV6": "fec0::3dc9:cc33:37de:42bd",
            "FRAME": "riscv64",
            "NIC": "eth0",
            "MAC": "52:54:00:12:34:56",
            "IPV4": "10.0.2.15",
            "USER": "root",
            "PASSWORD": "openEuler12#$",
            "SSH_PORT": 22,
            "BMC_IP": "",
            "BMC_USER": "",
            "BMC_PASSWORD": ""
        }
    ]
}